Metadata-Version: 2.0
Name: odoo9-addon-project-task-materials-stock
Version: 9.0.1.2.0
Summary: Create stock and analytic moves from record products spent in a Task
Home-page: UNKNOWN
Author: Antiun Ingeniería S.L.,Tecnativa, Odoo Community Association (OCA)
Author-email: support@odoo-community.org
License: AGPL-3
Platform: UNKNOWN
Classifier: Programming Language :: Python :: 2.7
Classifier: Framework :: Odoo
Classifier: License :: OSI Approved :: GNU Affero General Public License v3
Requires-Dist: odoo (<9.1a,>=9.0a)
Requires-Dist: odoo9-addon-project-task-materials
